flake8_awesome/__init__.py
flake8_awesome-1.3.0.dist-info/LICENSE
flake8_awesome-1.3.0.dist-info/WHEEL
flake8_awesome-1.3.0.dist-info/METADATA
flake8_awesome-1.3.0.dist-info/RECORD
