Metadata-Version: 2.1
Name: flake8-awesome
Version: 1.3.0
Summary: Flake8 awesome plugins pack
Home-page: https://pypi.org/project/flake8-awesome
License: MIT
Keywords: flake8,plugin
Author: Afonasev Evgeniy
Author-email: ea.afonasev@gmail.com
Requires-Python: >=3.6,<4.0
Classifier: License :: OSI Approved :: MIT License
Classifier: Programming Language :: Python :: 3
Classifier: Programming Language :: Python :: 3.6
Classifier: Programming Language :: Python :: 3.7
Classifier: Programming Language :: Python :: 3.8
Requires-Dist: flake8
Requires-Dist: flake8-annotations-complexity
Requires-Dist: flake8-bandit
Requires-Dist: flake8-breakpoint
Requires-Dist: flake8-bugbear
Requires-Dist: flake8-builtins
Requires-Dist: flake8-comprehensions
Requires-Dist: flake8-eradicate
Requires-Dist: flake8-expression-complexity
Requires-Dist: flake8-if-expr
Requires-Dist: flake8-isort
Requires-Dist: flake8-logging-format
Requires-Dist: flake8-print
Requires-Dist: flake8-pytest
Requires-Dist: flake8-pytest-style
Requires-Dist: flake8-requirements
Requires-Dist: flake8-return
Requires-Dist: pep8-naming
Project-URL: Repository, https://github.com/afonasev/flake8-awesome
